{
    "MRMOVIE": {
        "banneduntil": "2024/10/04",
        "BanReason": "Mass RDM / Police Targeting"
    },
    "Quandigious": {
        "banneduntil": "2024/10/04",
        "BanReason": "Mass RDM"
    },
    "KelBo69": {
        "banneduntil": "2024/09/30",
        "BanReason": "Camping/RDM"
    },
    "Trax9.mm": {
        "banneduntil": "2024/09/30",
        "BanReason": "Camping/RDM"
    },
    "Kim.jong.un51": {
        "banneduntil": "2024/10/01",
        "BanReason": "mass rdm and cop targeting"
    },
    "Killergames40": {
        "banneduntil": "2024/10/04",
        "BanReason": "Spawning Camping"
    },
    "?ban kabloom119": {
        "banneduntil": "2024/27/9",
        "BanReason": "Cop targeting"
    },
    "?ban sharkboy117": {
        "banneduntil": "2024/27/9",
        "BanReason": "Rdm"
    },
    "?ban TheSBD": {
        "banneduntil": "2024/27/9",
        "BanReason": "Cop targeting"
    },
    "?ban TheSDB": {
        "banneduntil": "2024/27/9",
        "BanReason": "Cop targeting"
    },
    "sharkboy117": {
        "banneduntil": "2024/27/9",
        "BanReason": "Rdm"
    },
    "jim.spring.37": {
        "banneduntil": "2024/10/04",
        "BanReason": "Mass RDM"
    },
    "Eggman46": {
        "banneduntil": "2024/10/04",
        "BanReason": "Mass RDM"
    },
    "Pluhnem": {
        "banneduntil": "2024/10/04",
        "BanReason": "Spawn Killing & RDM"
    },
    "dunkeroni": {
        "banneduntil": "2024/09/29",
        "BanReason": "RDM & Cop Targeting"
    },
    "Zayneyeet": {
        "banneduntil": "2024/10/05",
        "BanReason": "Mass RDM"
    },
    "Ranger_Edge": {
        "banneduntil": "2024/10/01",
        "BanReason": "mass rdm"
    },
    "GrandpaC0ckandBalls": {
        "banneduntil": "2100/02/07",
        "BanReason": "hard r"
    },
    "xmozyx": {
        "banneduntil": "2100/02/07",
        "BanReason": "hard r"
    },
    "wollfy1267": {
        "banneduntil": "2024/10/01",
        "BanReason": "mass rdm"
    },
    "T_0ATWAY": {
        "banneduntil": "2024/09/30",
        "BanReason": "RDM"
    },
    "Scringy.bingy": {
        "banneduntil": "2024/10/05",
        "BanReason": "Mass RDM"
    },
    "Smught": {
        "banneduntil": "2024/10/05",
        "BanReason": "Mass RDM"
    },
    "Radio123": {
        "banneduntil": "2024/9/30",
        "BanReason": "RDM and cop targeting"
    },
    "winner5473": {
        "banneduntil": "2024/10/03",
        "BanReason": "MASS RDM"
    },
    "tortoise07": {
        "banneduntil": "2024/10/01",
        "BanReason": "cop targeting"
    },
    "JINX_18": {
        "banneduntil": "2024/10/03",
        "BanReason": "cop targeting and rdm"
    }
}